nendo_plugin_textgen/__init__.py
nendo_plugin_textgen/config.py
nendo_plugin_textgen/plugin.py
nendo_plugin_textgen-0.1.1.dist-info/LICENSE
nendo_plugin_textgen-0.1.1.dist-info/METADATA
nendo_plugin_textgen-0.1.1.dist-info/WHEEL
nendo_plugin_textgen-0.1.1.dist-info/RECORD
