Metadata-Version: 2.1
Name: nendo-plugin-textgen
Version: 0.1.1
Summary: A text generation plugin using local LLMs or other text generation methods. Builds on top of `transformers` by Hugging Face.
Home-page: https://okio.ai
License: MIT
Keywords: AI,generative,music,okio,nendo,text generation,LLM,transformers,music analysis,song analysis
Author: Aaron Abebe
Author-email: aaron@okio.ai
Requires-Python: >=3.8,<3.11
Classifier: Development Status :: 5 - Production/Stable
Classifier: Intended Audience :: Developers
Classifier: License :: OSI Approved :: MIT License
Classifier: Operating System :: OS Independent
Classifier: Programming Language :: Python :: 3
Classifier: Programming Language :: Python :: 3.8
Classifier: Programming Language :: Python :: 3.9
Classifier: Programming Language :: Python :: 3.10
Classifier: Topic :: Multimedia :: Sound/Audio
Requires-Dist: accelerate (>=0.24.1,<0.25.0)
Requires-Dist: nendo (>=0.2.0,<0.3.0)
Requires-Dist: optimum (>=1.15.0,<2.0.0)
Requires-Dist: pydantic (>=2.4.2,<3.0.0)
Requires-Dist: tiktoken (>=0.3.3,<0.4.0)
Requires-Dist: transformers (>=4.37.2,<5.0.0)
Requires-Dist: transformers_stream_generator (>=0.0.4,<0.0.5)
Project-URL: Repository, https://github.com/okio-ai/nendo_plugin_textgen
